hobbit/__init__.py
hobbit/bootstrap.py
hobbit/devtools.py
hobbit/handlers/__init__.py
hobbit/handlers/bootstrap.py
hobbit/handlers/devtools.py
hobbit/static/bootstrap/rivendell/.gitignore.jinja2
hobbit/static/bootstrap/rivendell/Dockerfile.jinja2
hobbit/static/bootstrap/rivendell/deploy.sh.jinja2
hobbit/static/bootstrap/rivendell/docker-compose.yml.jinja2
hobbit/static/bootstrap/rivendell/pytest.ini.jinja2
hobbit/static/bootstrap/rivendell/requirements.txt.jinja2
hobbit/static/bootstrap/rivendell/app/__init__.py.jinja2
hobbit/static/bootstrap/rivendell/app/exts.py.jinja2
hobbit/static/bootstrap/rivendell/app/run.py.jinja2
hobbit/static/bootstrap/rivendell/app/configs/__init__.py.jinja2
hobbit/static/bootstrap/rivendell/app/configs/default.py.jinja2
hobbit/static/bootstrap/rivendell/app/configs/development.py.jinja2
hobbit/static/bootstrap/rivendell/app/configs/production.py.jinja2
hobbit/static/bootstrap/rivendell/app/configs/testing.py.jinja2
hobbit/static/bootstrap/rivendell/app/core/__init__.py.jinja2
hobbit/static/bootstrap/rivendell/app/models/__init__.py.jinja2
hobbit/static/bootstrap/rivendell/app/models/consts.py.jinja2
hobbit/static/bootstrap/rivendell/app/schemas/__init__.py.jinja2
hobbit/static/bootstrap/rivendell/app/services/__init__.py.jinja2
hobbit/static/bootstrap/rivendell/app/services/tools.py.jinja2
hobbit/static/bootstrap/rivendell/app/utils/__init__.py.jinja2
hobbit/static/bootstrap/rivendell/app/views/__init__.py.jinja2
hobbit/static/bootstrap/rivendell/app/views/tools.py.jinja2
hobbit/static/bootstrap/rivendell/configs/gunicorn-logging.ini.jinja2
hobbit/static/bootstrap/rivendell/docs/index.apib.jinja2
hobbit/static/bootstrap/rivendell/tests/__init__.py.jinja2
hobbit/static/bootstrap/rivendell/tests/conftest.py.jinja2
hobbit/static/bootstrap/rivendell/tests/test_tools.py.jinja2
hobbit/static/bootstrap/shire/.gitignore.jinja2
hobbit/static/bootstrap/shire/.gitlab-ci.yml.jinja2
hobbit/static/bootstrap/shire/Dockerfile.jinja2
hobbit_core-4.0.0.dist-info/LICENSE
hobbit_core-4.0.0.dist-info/METADATA
hobbit_core-4.0.0.dist-info/WHEEL
hobbit_core-4.0.0.dist-info/entry_points.txt
hobbit_core-4.0.0.dist-info/top_level.txt
hobbit_core-4.0.0.dist-info/RECORD
