Metadata-Version: 2.1
Name: hobbit-core
Version: 4.0.0
Summary: Hobbit - A flask project generator.
Home-page: https://github.com/TTWShell/hobbit-core
Author: Legolas Bloom
Author-email: zhanhsw@gmail.com
Classifier: Topic :: Utilities
Classifier: Programming Language :: Python :: 3.8
Classifier: Programming Language :: Python :: 3.9
Classifier: Programming Language :: Python :: 3.10
Classifier: Programming Language :: Python :: 3.11
Classifier: Programming Language :: Python :: 3.12
Classifier: Programming Language :: Python :: Implementation :: CPython
Classifier: License :: OSI Approved :: MIT License
Requires-Python: >=3.8, <4
License-File: LICENSE
Provides-Extra: hobbit
Requires-Dist: Click>=6.7; extra == "hobbit"
Requires-Dist: Jinja2>=3.0; extra == "hobbit"
Requires-Dist: inflect>=2.1.0; extra == "hobbit"
Requires-Dist: markupsafe>=2.0.1; extra == "hobbit"
Provides-Extra: hobbit_core
Requires-Dist: Flask<4,>=3.0; extra == "hobbit-core"
Requires-Dist: flask-marshmallow<2,>=1.0; extra == "hobbit-core"
Requires-Dist: Flask-Migrate<5,>=4; extra == "hobbit-core"
Requires-Dist: flask-shell-ipython>=0.4.1; extra == "hobbit-core"
Requires-Dist: SQLAlchemy<3,>=2.0; extra == "hobbit-core"
Requires-Dist: Flask-SQLAlchemy<4,>=3.0.0; extra == "hobbit-core"
Requires-Dist: marshmallow<4,>=3.0.0; extra == "hobbit-core"
Requires-Dist: marshmallow-enum<2,>=1.5.1; extra == "hobbit-core"
Requires-Dist: marshmallow-sqlalchemy<3,>=0.26.1; extra == "hobbit-core"
Requires-Dist: webargs<9,>=8.0.0; extra == "hobbit-core"
Requires-Dist: mypy-extensions>=0.4.3; extra == "hobbit-core"
Requires-Dist: pyyaml!=5.4.0,!=5.4.1,!=6.0.0; extra == "hobbit-core"
